restcountries_cli/__init__.py
restcountries_cli/cli.py
restcountries_cli/constants.py
restcountries_cli/exceptions.py
restcountries_cli/factories.py
restcountries_cli/models.py
restcountries_cli-0.0.1.dist-info/LICENSE
restcountries_cli-0.0.1.dist-info/METADATA
restcountries_cli-0.0.1.dist-info/WHEEL
restcountries_cli-0.0.1.dist-info/RECORD
